Metadata-Version: 1.0
Name: dz
Version: 0.1.1
Summary: deploy zone
Home-page: https://github.com/wiedi/dz
Author: Sebastian Wiedenroth
Author-email: sw@core.io
License: UNKNOWN
Platform: UNKNOWN
